chainrand/__init__.py
chainrand-0.0.1.dist-info/LICENSE.txt
chainrand-0.0.1.dist-info/METADATA
chainrand-0.0.1.dist-info/WHEEL
chainrand-0.0.1.dist-info/top_level.txt
chainrand-0.0.1.dist-info/RECORD
