Metadata-Version: 2.1
Name: chainrand
Version: 0.0.1
Summary: UNKNOWN
Home-page: https://github.com/chainrand/chainrand-py
Author: Kang Yue Sheng Benjamin
Author-email: chainrand@gmail.com
License: MIT
Keywords: chainrand chainlink vrf provenance crypto blockchain nft opensea ethereum eth matic polygon academic integrity ipfs sha256 aes256
Platform: UNKNOWN
License-File: LICENSE.txt
Requires-Dist: pycrypto
